rtl/irom.sv
`timescale 1ns/1ps

module irom (
    input  logic [31:0] addr,
    output logic [31:0] instr
);

    logic [31:0] mem [0:255];   // 256 words = 1KB of program space

    // Hardcoded program for now
    initial begin
        // We'll fill this in below
        mem[0] = 32'h00A00293;  // addi x5, x0, 10
        mem[1] = 32'h01400313;  // addi x6, x0, 20
        mem[2] = 32'h006283B3;  // add  x7, x5, x6
        mem[3] = 32'h00702023;  // sw   x7, 0(x0)
        mem[4] = 32'h00002403;  // lw   x8, 0(x0)
    end

    assign instr = mem[addr[11:2]];   // same byte→word trick as DMEM!

endmodule

bidrv32.sv
module bidrv32 (
    input logic clk,
    input logic rstn,

    output logic [31:0] pc,
    input logic [31:0] instr
);

// PC register
always_ff @(posedge clk or negedge rstn) begin
    if (!rstn) pc <= 32'd0;
    else pc <= pc + 32'd4;
end

// Decoder
logic [6:0] opcode, funct7;
logic [4:0] rd, rs1, rs2;
logic [2:0] funct3;

assign opcode = instr[6:0];
assign rd = instr[11:7];
assign funct3 = instr[14:12];
assign rs1 = instr[19:15];
assign rs2 = instr[24:20];
assign funct7 = instr[31:25];

logic [31:0] imm;

always_comb begin
    case (opcode)
        7'b0010011: imm = {{20{instr[31]}}, instr[31:20]};  // I-type
        7'b0000011: imm = {{20{instr[31]}}, instr[31:20]};  // Load
        7'b0100011: imm = {{20{instr[31]}}, instr[31:25], instr[11:7]};  // S-type
        7'b1100011: imm = {{19{instr[31]}}, instr[31], instr[7], instr[30:25], instr[11:8], 1'b0}; // B-type
        7'b0110111: imm = {instr[31:12], 12'b0};  // U-type
        7'b1101111: imm = {{11{instr[31]}}, instr[31], instr[19:12], instr[20], instr[30:21], 1'b0}; // J-type
        default:    imm = 32'b0;  // R-type has no immediate
    endcase
end

// Control Unit
logic we;
logic alu_src, mem_read, mem_write, mem_to_reg;
logic [3:0] alu_op;

always_comb begin
    we = 0;
    alu_src = 0;
    mem_read = 0;
    mem_write = 0;
    alu_op = 4'b0;
    mem_to_reg = 0;

    case (opcode) 
        7'b0110011: begin  // R-type
            we      = 1;
            alu_src = 0;
            case ({funct7[5], funct3}) 
                4'b0000: alu_op = 4'b0000; // ADD
                4'b1000: alu_op = 4'b0001; // SUB
                4'b0111: alu_op = 4'b0010; // AND
                4'b0110: alu_op = 4'b0011; // OR
                4'b0100: alu_op = 4'b0100; // XOR
                4'b0001: alu_op = 4'b0101; // SLL
                4'b0101: alu_op = 4'b0110; // SRL
                4'b1101: alu_op = 4'b0111; // SRA
                4'b0010: alu_op = 4'b1000; // SLT
                default: alu_op = 4'b0000;
            endcase
        end
        7'b0010011: begin  // I-type (Immediate-type)
            we      = 1;
            alu_src = 1;
            alu_op  = 4'b0000;
        end
        7'b0000011: begin  // Load
            we       = 1;
            alu_src  = 1;
            mem_read = 1;
            alu_op  = 4'b0000;
            mem_to_reg = 1;
        end
        7'b0100011: begin  // S-type (Store) 
            alu_src   = 1;
            mem_write = 1;
            alu_op  = 4'b0000;
        end
        7'b1100011: begin  // B-type (Branch)
            alu_op  = 4'b0001;
        end
        //later will add U (Upper-immediate) and J (Jump) type
    endcase
end

// Register file
logic [31:0] wd, rdata1, rdata2;

logic [31:0] regs [0:31];
always_ff @(posedge clk or negedge rstn) begin
    if (!rstn) begin
        for (int i =0; i<32; i++)
            regs[i] <= 32'b0;
    end 
    else if (we && (rd != 0)) begin
        regs[rd] <= wd;
    end
end

assign rdata1 = (rs1 == 0) ? 32'b0 : regs[rs1];
assign rdata2 = (rs2 == 0) ? 32'b0 : regs[rs2];

// ALU
logic [31:0] alu_input_b, alu_result;
logic alu_out_zero;

assign alu_input_b = (alu_src == 0) ? rdata2 : imm;

always_comb begin
    case (alu_op)
        4'b0000: alu_result = rdata1 + alu_input_b;           // ADD
        4'b0001: alu_result = rdata1 - alu_input_b;           // SUB
        4'b0010: alu_result = rdata1 & alu_input_b;           // AND
        4'b0011: alu_result = rdata1 | alu_input_b;           // OR
        4'b0100: alu_result = rdata1 ^ alu_input_b;           // XOR
        4'b0101: alu_result = rdata1 << alu_input_b[4:0];     // SLL
        4'b0110: alu_result = rdata1 >> alu_input_b[4:0];     // SRL
        4'b0111: alu_result = $signed(rdata1) >>> alu_input_b[4:0]; // SRA
        4'b1000: alu_result = ($signed(rdata1) < $signed(alu_input_b)) ? 32'd1 : 32'd0; // SLT
        default: alu_result = 32'b0;
    endcase
end

assign alu_out_zero = (alu_result == 32'b0);

logic [31:0] mem_rdata;
assign wd = (mem_to_reg == 0) ? alu_result : mem_rdata;

//DMEM
logic [31:0] dmem [0:1023];   // 1024 words = 4 KB

always_ff @(posedge clk) begin
    if (mem_write)
        dmem[alu_result[11:2]] <= rdata2;
end

assign mem_rdata = (mem_read) ? dmem[alu_result[11:2]] : 32'b0;
endmodule

tb/testbench.sv
`timescale 1ns/1ps

module tb_top;

    logic clk, rstn;
    logic [31:0] pc, instr;

    // Clock generator — 10ns period (100MHz)
    initial clk = 0;
    always #5 clk = ~clk;

    // Reset sequence
    initial begin
        rstn = 0;
        #20;
        rstn = 1;
    end

    // Instantiate CPU
    bidrv32 cpu (
        .clk(clk),
        .rstn(rstn),
        .pc(pc),
        .instr(instr)
    );

    // Instantiate ROM
    irom rom (
        .addr(pc),
        .instr(instr)
    );

    // Simulation control
    initial begin
        $dumpfile("wave.vcd");
        $dumpvars(0, tb_top);
        #200;
        $finish;
    end

    // Print regs after every clock edge for visibility
    always @(posedge clk) begin
        $display("t=%0t  pc=%h  instr=%h  x5=%0d  x6=%0d  x7=%0d  x8=%0d",
        $time, pc, instr, cpu.regs[5], cpu.regs[6], cpu.regs[7], cpu.regs[8]);
    end

endmodule

build/wave.vcd
$date
	Tue May 19 16:44:01 2026
$end
$version
	Icarus Verilog
$end
$timescale
	1ps
$end
$scope module tb_top $end
$var wire 32 ! pc [31:0] $end
$var wire 32 " instr [31:0] $end
$var reg 1 # clk $end
$var reg 1 $ rstn $end
$scope module cpu $end
$var wire 1 # clk $end
$var wire 1 $ rstn $end
$var wire 32 % wd [31:0] $end
$var wire 5 & rs2 [4:0] $end
$var wire 5 ' rs1 [4:0] $end
$var wire 32 ( rdata2 [31:0] $end
$var wire 32 ) rdata1 [31:0] $end
$var wire 5 * rd [4:0] $end
$var wire 7 + opcode [6:0] $end
$var wire 32 , mem_rdata [31:0] $end
$var wire 32 - instr [31:0] $end
$var wire 7 . funct7 [6:0] $end
$var wire 3 / funct3 [2:0] $end
$var wire 1 0 alu_out_zero $end
$var wire 32 1 alu_input_b [31:0] $end
$var reg 4 2 alu_op [3:0] $end
$var reg 32 3 alu_result [31:0] $end
$var reg 1 4 alu_src $end
$var reg 32 5 imm [31:0] $end
$var reg 1 6 mem_read $end
$var reg 1 7 mem_to_reg $end
$var reg 1 8 mem_write $end
$var reg 32 9 pc [31:0] $end
$var reg 1 : we $end
$scope begin $ivl_for_loop0 $end
$var integer 32 ; i [31:0] $end
$upscope $end
$upscope $end
$scope module rom $end
$var wire 32 < addr [31:0] $end
$var wire 32 = instr [31:0] $end
$upscope $end
$upscope $end
$enddefinitions $end
$comment Show the parameter values. $end
$dumpall
$end
#0
$dumpvars
b101000000000001010010011 =
b0 <
b100000 ;
1:
b0 9
08
07
06
b1010 5
14
b1010 3
b0 2
b1010 1
00
b0 /
b0 .
b101000000000001010010011 -
b0 ,
b10011 +
b101 *
b0 )
b0 (
b0 '
b1010 &
b1010 %
0$
0#
b101000000000001010010011 "
b0 !
$end
#5000
b100000 ;
1#
#10000
0#
#15000
b100000 ;
1#
#20000
0#
1$
#25000
b10100 %
b10100 3
b10100 1
b10100 &
b110 *
b10100 5
b1010000000000001100010011 "
b1010000000000001100010011 -
b1010000000000001100010011 =
b100 !
b100 9
b100 <
1#
#30000
0#
#35000
b11110 %
b11110 3
b10100 (
b1010 )
04
1:
b10100 1
b110 &
b101 '
b111 *
b110011 +
b0 5
b11000101000001110110011 "
b11000101000001110110011 -
b11000101000001110110011 =
b1000 !
b1000 9
b1000 <
1#
#40000
0#
#45000
b0 %
10
b0 3
b0 1
b11110 (
b0 )
18
14
0:
b111 &
b0 '
b10 /
b0 *
b100011 +
b11100000010000000100011 "
b11100000010000000100011 -
b11100000010000000100011 =
b1100 !
b1100 9
b1100 <
1#
#50000
0#
#55000
b11110 %
b11110 ,
10
b0 3
b0 (
17
16
1:
08
14
b0 1
b0 &
b1000 *
b11 +
b0 5
b10010000000011 "
b10010000000011 -
b10010000000011 =
b10000 !
b10000 9
b10000 <
1#
#60000
0#
#65000
bx %
b0 ,
x0
bx 3
bx (
bx )
07
06
04
0:
bx 1
bx .
bx &
bx '
bx /
bx *
bx +
b0 5
bx "
bx -
bx =
b10100 !
b10100 9
b10100 <
1#
#70000
0#
#75000
b11000 !
b11000 9
b11000 <
1#
#80000
0#
#85000
b11100 !
b11100 9
b11100 <
1#
#90000
0#
#95000
b100000 !
b100000 9
b100000 <
1#
#100000
0#
#105000
b100100 !
b100100 9
b100100 <
1#
#110000
0#
#115000
b101000 !
b101000 9
b101000 <
1#
#120000
0#
#125000
b101100 !
b101100 9
b101100 <
1#
#130000
0#
#135000
b110000 !
b110000 9
b110000 <
1#
#140000
0#
#145000
b110100 !
b110100 9
b110100 <
1#
#150000
0#
#155000
b111000 !
b111000 9
b111000 <
1#
#160000
0#
#165000
b111100 !
b111100 9
b111100 <
1#
#170000
0#
#175000
b1000000 !
b1000000 9
b1000000 <
1#
#180000
0#
#185000
b1000100 !
b1000100 9
b1000100 <
1#
#190000
0#
#195000
b1001000 !
b1001000 9
b1001000 <
1#
